Classfile /C:/PROJECT/project3/app/build/tmp/kotlin-classes/debug/com/example/project3/AudioSegmentDownloader.class
  Last modified 2026. 4. 21.; size 6784 bytes
  SHA-256 checksum c082a37e3cc4568e33255a967f1b5d3f943601b1f68b27ad4bc30d0351098f0c
  Compiled from "AudioSegmentDownloader.kt"
public final class com.example.project3.AudioSegmentDownloader
  minor version: 0
  major version: 61
  flags: (0x0031) ACC_PUBLIC, ACC_FINAL, ACC_SUPER
  this_class: #2                          // com/example/project3/AudioSegmentDownloader
  super_class: #4                         // java/lang/Object
  interfaces: 0, fields: 1, methods: 3, attributes: 5
Constant pool:
    #1 = Utf8               com/example/project3/AudioSegmentDownloader
    #2 = Class              #1            // com/example/project3/AudioSegmentDownloader
    #3 = Utf8               java/lang/Object
    #4 = Class              #3            // java/lang/Object
    #5 = Utf8               <init>
    #6 = Utf8               (Landroid/content/Context;)V
    #7 = Utf8               Lorg/jetbrains/annotations/NotNull;
    #8 = Utf8               context
    #9 = String             #8            // context
   #10 = Utf8               kotlin/jvm/internal/Intrinsics
   #11 = Class              #10           // kotlin/jvm/internal/Intrinsics
   #12 = Utf8               checkNotNullParameter
   #13 = Utf8               (Ljava/lang/Object;Ljava/lang/String;)V
   #14 = NameAndType        #12:#13       // checkNotNullParameter:(Ljava/lang/Object;Ljava/lang/String;)V
   #15 = Methodref          #11.#14       // kotlin/jvm/internal/Intrinsics.checkNotNullParameter:(Ljava/lang/Object;Ljava/lang/String;)V
   #16 = Utf8               ()V
   #17 = NameAndType        #5:#16        // "<init>":()V
   #18 = Methodref          #4.#17        // java/lang/Object."<init>":()V
   #19 = Utf8               Landroid/content/Context;
   #20 = NameAndType        #8:#19        // context:Landroid/content/Context;
   #21 = Fieldref           #2.#20        // com/example/project3/AudioSegmentDownloader.context:Landroid/content/Context;
   #22 = Utf8               this
   #23 = Utf8               Lcom/example/project3/AudioSegmentDownloader;
   #24 = Utf8               cutSegmentFromLocal
   #25 = Utf8               (Ljava/lang/String;II)Ljava/io/File;
   #26 = Utf8               java/lang/Throwable
   #27 = Class              #26           // java/lang/Throwable
   #28 = Utf8               localSourcePath
   #29 = String             #28           // localSourcePath
   #30 = Utf8               endSec must be greater than startSec
   #31 = String             #30           // endSec must be greater than startSec
   #32 = Utf8               java/lang/IllegalArgumentException
   #33 = Class              #32           // java/lang/IllegalArgumentException
   #34 = Utf8               toString
   #35 = Utf8               ()Ljava/lang/String;
   #36 = NameAndType        #34:#35       // toString:()Ljava/lang/String;
   #37 = Methodref          #4.#36        // java/lang/Object.toString:()Ljava/lang/String;
   #38 = Utf8               (Ljava/lang/String;)V
   #39 = NameAndType        #5:#38        // "<init>":(Ljava/lang/String;)V
   #40 = Methodref          #33.#39       // java/lang/IllegalArgumentException."<init>":(Ljava/lang/String;)V
   #41 = Utf8               java/io/File
   #42 = Class              #41           // java/io/File
   #43 = Utf8               android/content/Context
   #44 = Class              #43           // android/content/Context
   #45 = Utf8               getExternalFilesDir
   #46 = Utf8               (Ljava/lang/String;)Ljava/io/File;
   #47 = NameAndType        #45:#46       // getExternalFilesDir:(Ljava/lang/String;)Ljava/io/File;
   #48 = Methodref          #44.#47       // android/content/Context.getExternalFilesDir:(Ljava/lang/String;)Ljava/io/File;
   #49 = Utf8               segments
   #50 = String             #49           // segments
   #51 = Utf8               (Ljava/io/File;Ljava/lang/String;)V
   #52 = NameAndType        #5:#51        // "<init>":(Ljava/io/File;Ljava/lang/String;)V
   #53 = Methodref          #42.#52       // java/io/File."<init>":(Ljava/io/File;Ljava/lang/String;)V
   #54 = Utf8               mkdirs
   #55 = Utf8               ()Z
   #56 = NameAndType        #54:#55       // mkdirs:()Z
   #57 = Methodref          #42.#56       // java/io/File.mkdirs:()Z
   #58 = Utf8               java/lang/System
   #59 = Class              #58           // java/lang/System
   #60 = Utf8               currentTimeMillis
   #61 = Utf8               ()J
   #62 = NameAndType        #60:#61       // currentTimeMillis:()J
   #63 = Methodref          #59.#62       // java/lang/System.currentTimeMillis:()J
   #64 = Utf8               seg-\u0001-\u0001s-\u0001s
   #65 = String             #64           // seg-\u0001-\u0001s-\u0001s
   #66 = Utf8               java/lang/invoke/StringConcatFactory
   #67 = Class              #66           // java/lang/invoke/StringConcatFactory
   #68 = Utf8               makeConcatWithConstants
   #69 = Utf8               (Ljava/lang/invoke/MethodHandles$Lookup;Ljava/lang/String;Ljava/lang/invoke/MethodType;Ljava/lang/String;[Ljava/lang/Object;)Ljava/lang/invoke/CallSite;
   #70 = NameAndType        #68:#69       // makeConcatWithConstants:(Ljava/lang/invoke/MethodHandles$Lookup;Ljava/lang/String;Ljava/lang/invoke/MethodType;Ljava/lang/String;[Ljava/lang/Object;)Ljava/lang/invoke/CallSite;
   #71 = Methodref          #67.#70       // java/lang/invoke/StringConcatFactory.makeConcatWithConstants:(Ljava/lang/invoke/MethodHandles$Lookup;Ljava/lang/String;Ljava/lang/invoke/MethodType;Ljava/lang/String;[Ljava/lang/Object;)Ljava/lang/invoke/CallSite;
   #72 = MethodHandle       6:#71         // REF_invokeStatic java/lang/invoke/StringConcatFactory.makeConcatWithConstants:(Ljava/lang/invoke/MethodHandles$Lookup;Ljava/lang/String;Ljava/lang/invoke/MethodType;Ljava/lang/String;[Ljava/lang/Object;)Ljava/lang/invoke/CallSite;
   #73 = Utf8               (JII)Ljava/lang/String;
   #74 = NameAndType        #68:#73       // makeConcatWithConstants:(JII)Ljava/lang/String;
   #75 = InvokeDynamic      #0:#74        // #0:makeConcatWithConstants:(JII)Ljava/lang/String;
   #76 = Methodref          #42.#39       // java/io/File."<init>":(Ljava/lang/String;)V
   #77 = Utf8               kotlin/io/FilesKt
   #78 = Class              #77           // kotlin/io/FilesKt
   #79 = Utf8               getExtension
   #80 = Utf8               (Ljava/io/File;)Ljava/lang/String;
   #81 = NameAndType        #79:#80       // getExtension:(Ljava/io/File;)Ljava/lang/String;
   #82 = Methodref          #78.#81       // kotlin/io/FilesKt.getExtension:(Ljava/io/File;)Ljava/lang/String;
   #83 = Utf8               java/util/Locale
   #84 = Class              #83           // java/util/Locale
   #85 = Utf8               ROOT
   #86 = Utf8               Ljava/util/Locale;
   #87 = NameAndType        #85:#86       // ROOT:Ljava/util/Locale;
   #88 = Fieldref           #84.#87       // java/util/Locale.ROOT:Ljava/util/Locale;
   #89 = Utf8               java/lang/String
   #90 = Class              #89           // java/lang/String
   #91 = Utf8               toLowerCase
   #92 = Utf8               (Ljava/util/Locale;)Ljava/lang/String;
   #93 = NameAndType        #91:#92       // toLowerCase:(Ljava/util/Locale;)Ljava/lang/String;
   #94 = Methodref          #90.#93       // java/lang/String.toLowerCase:(Ljava/util/Locale;)Ljava/lang/String;
   #95 = Utf8               toLowerCase(...)
   #96 = String             #95           // toLowerCase(...)
   #97 = Utf8               checkNotNullExpressionValue
   #98 = NameAndType        #97:#13       // checkNotNullExpressionValue:(Ljava/lang/Object;Ljava/lang/String;)V
   #99 = Methodref          #11.#98       // kotlin/jvm/internal/Intrinsics.checkNotNullExpressionValue:(Ljava/lang/Object;Ljava/lang/String;)V
  #100 = Utf8               java/lang/CharSequence
  #101 = Class              #100          // java/lang/CharSequence
  #102 = Utf8               kotlin/text/StringsKt
  #103 = Class              #102          // kotlin/text/StringsKt
  #104 = Utf8               isBlank
  #105 = Utf8               (Ljava/lang/CharSequence;)Z
  #106 = NameAndType        #104:#105     // isBlank:(Ljava/lang/CharSequence;)Z
  #107 = Methodref          #103.#106     // kotlin/text/StringsKt.isBlank:(Ljava/lang/CharSequence;)Z
  #108 = Utf8               webm
  #109 = String             #108          // webm
  #110 = Utf8               hashCode
  #111 = Utf8               ()I
  #112 = NameAndType        #110:#111     // hashCode:()I
  #113 = Methodref          #90.#112      // java/lang/String.hashCode:()I
  #114 = Utf8               mp4
  #115 = String             #114          // mp4
  #116 = Utf8               equals
  #117 = Utf8               (Ljava/lang/Object;)Z
  #118 = NameAndType        #116:#117     // equals:(Ljava/lang/Object;)Z
  #119 = Methodref          #90.#118      // java/lang/String.equals:(Ljava/lang/Object;)Z
  #120 = Utf8               aac
  #121 = String             #120          // aac
  #122 = Utf8               m4a
  #123 = String             #122          // m4a
  #124 = Utf8               \u0001.\u0001
  #125 = String             #124          // \u0001.\u0001
  #126 = Utf8               (Ljava/lang/String;Ljava/lang/String;)Ljava/lang/String;
  #127 = NameAndType        #68:#126      // makeConcatWithConstants:(Ljava/lang/String;Ljava/lang/String;)Ljava/lang/String;
  #128 = InvokeDynamic      #1:#127       // #1:makeConcatWithConstants:(Ljava/lang/String;Ljava/lang/String;)Ljava/lang/String;
  #129 = Utf8               escapeForCli
  #130 = Utf8               (Ljava/lang/String;)Ljava/lang/String;
  #131 = NameAndType        #129:#130     // escapeForCli:(Ljava/lang/String;)Ljava/lang/String;
  #132 = Methodref          #2.#131       // com/example/project3/AudioSegmentDownloader.escapeForCli:(Ljava/lang/String;)Ljava/lang/String;
  #133 = Utf8               java/lang/StringBuilder
  #134 = Class              #133          // java/lang/StringBuilder
  #135 = Methodref          #134.#17      // java/lang/StringBuilder."<init>":()V
  #136 = Utf8               -y -hide_banner -loglevel error -nostdin
  #137 = String             #136          // -y -hide_banner -loglevel error -nostdin
  #138 = Utf8               append
  #139 = Utf8               (Ljava/lang/String;)Ljava/lang/StringBuilder;
  #140 = NameAndType        #138:#139     // append:(Ljava/lang/String;)Ljava/lang/StringBuilder;
  #141 = Methodref          #134.#140     // java/lang/StringBuilder.append:(Ljava/lang/String;)Ljava/lang/StringBuilder;
  #142 = Utf8               getAbsolutePath
  #143 = NameAndType        #142:#35      // getAbsolutePath:()Ljava/lang/String;
  #144 = Methodref          #42.#143      // java/io/File.getAbsolutePath:()Ljava/lang/String;
  #145 = Utf8               -ss \u0001 -to \u0001 -i \"\u0001\" -vn -c:a copy \"\u0001\"
  #146 = String             #145          // -ss \u0001 -to \u0001 -i \"\u0001\" -vn -c:a copy \"\u0001\"
  #147 = Utf8               (IILjava/lang/String;Ljava/lang/String;)Ljava/lang/String;
  #148 = NameAndType        #68:#147      // makeConcatWithConstants:(IILjava/lang/String;Ljava/lang/String;)Ljava/lang/String;
  #149 = InvokeDynamic      #2:#148       // #2:makeConcatWithConstants:(IILjava/lang/String;Ljava/lang/String;)Ljava/lang/String;
  #150 = Methodref          #134.#36      // java/lang/StringBuilder.toString:()Ljava/lang/String;
  #151 = Utf8               toString(...)
  #152 = String             #151          // toString(...)
  #153 = Utf8               com/arthenica/ffmpegkit/FFmpegKit
  #154 = Class              #153          // com/arthenica/ffmpegkit/FFmpegKit
  #155 = Utf8               execute
  #156 = Utf8               (Ljava/lang/String;)Lcom/arthenica/ffmpegkit/FFmpegSession;
  #157 = NameAndType        #155:#156     // execute:(Ljava/lang/String;)Lcom/arthenica/ffmpegkit/FFmpegSession;
  #158 = Methodref          #154.#157     // com/arthenica/ffmpegkit/FFmpegKit.execute:(Ljava/lang/String;)Lcom/arthenica/ffmpegkit/FFmpegSession;
  #159 = Utf8               com/arthenica/ffmpegkit/FFmpegSession
  #160 = Class              #159          // com/arthenica/ffmpegkit/FFmpegSession
  #161 = Utf8               getReturnCode
  #162 = Utf8               ()Lcom/arthenica/ffmpegkit/ReturnCode;
  #163 = NameAndType        #161:#162     // getReturnCode:()Lcom/arthenica/ffmpegkit/ReturnCode;
  #164 = Methodref          #160.#163     // com/arthenica/ffmpegkit/FFmpegSession.getReturnCode:()Lcom/arthenica/ffmpegkit/ReturnCode;
  #165 = Utf8               com/arthenica/ffmpegkit/ReturnCode
  #166 = Class              #165          // com/arthenica/ffmpegkit/ReturnCode
  #167 = Utf8               isValueSuccess
  #168 = NameAndType        #167:#55      // isValueSuccess:()Z
  #169 = Methodref          #166.#168     // com/arthenica/ffmpegkit/ReturnCode.isValueSuccess:()Z
  #170 = Utf8               exists
  #171 = NameAndType        #170:#55      // exists:()Z
  #172 = Methodref          #42.#171      // java/io/File.exists:()Z
  #173 = Utf8               length
  #174 = NameAndType        #173:#61      // length:()J
  #175 = Methodref          #42.#174      // java/io/File.length:()J
  #176 = Long               1024l
  #178 = Utf8               \u0001.opus
  #179 = String             #178          // \u0001.opus
  #180 = NameAndType        #68:#130      // makeConcatWithConstants:(Ljava/lang/String;)Ljava/lang/String;
  #181 = InvokeDynamic      #3:#180       // #3:makeConcatWithConstants:(Ljava/lang/String;)Ljava/lang/String;
  #182 = Utf8               -ss \u0001 -to \u0001 -i \"\u0001\" -vn -c:a libopus -b:a 64k \"\u0001\"
  #183 = String             #182          // -ss \u0001 -to \u0001 -i \"\u0001\" -vn -c:a libopus -b:a 64k \"\u0001\"
  #184 = InvokeDynamic      #4:#148       // #4:makeConcatWithConstants:(IILjava/lang/String;Ljava/lang/String;)Ljava/lang/String;
  #185 = Utf8               kotlin/Result
  #186 = Class              #185          // kotlin/Result
  #187 = Utf8               Companion
  #188 = Utf8               Lkotlin/Result$Companion;
  #189 = NameAndType        #187:#188     // Companion:Lkotlin/Result$Companion;
  #190 = Fieldref           #186.#189     // kotlin/Result.Companion:Lkotlin/Result$Companion;
  #191 = Utf8               getAllLogsAsString
  #192 = NameAndType        #191:#35      // getAllLogsAsString:()Ljava/lang/String;
  #193 = Methodref          #160.#192     // com/arthenica/ffmpegkit/FFmpegSession.getAllLogsAsString:()Ljava/lang/String;
  #194 = Utf8               constructor-impl
  #195 = Utf8               (Ljava/lang/Object;)Ljava/lang/Object;
  #196 = NameAndType        #194:#195     // "constructor-impl":(Ljava/lang/Object;)Ljava/lang/Object;
  #197 = Methodref          #186.#196     // kotlin/Result."constructor-impl":(Ljava/lang/Object;)Ljava/lang/Object;
  #198 = Utf8               kotlin/ResultKt
  #199 = Class              #198          // kotlin/ResultKt
  #200 = Utf8               createFailure
  #201 = Utf8               (Ljava/lang/Throwable;)Ljava/lang/Object;
  #202 = NameAndType        #200:#201     // createFailure:(Ljava/lang/Throwable;)Ljava/lang/Object;
  #203 = Methodref          #199.#202     // kotlin/ResultKt.createFailure:(Ljava/lang/Throwable;)Ljava/lang/Object;
  #204 = Utf8               isFailure-impl
  #205 = NameAndType        #204:#117     // "isFailure-impl":(Ljava/lang/Object;)Z
  #206 = Methodref          #186.#205     // kotlin/Result."isFailure-impl":(Ljava/lang/Object;)Z
  #207 = Utf8
  #208 = String             #207          //
  #209 = Utf8               java/lang/IllegalStateException
  #210 = Class              #209          // java/lang/IllegalStateException
  #211 = Utf8               takeLast
  #212 = Utf8               (Ljava/lang/String;I)Ljava/lang/String;
  #213 = NameAndType        #211:#212     // takeLast:(Ljava/lang/String;I)Ljava/lang/String;
  #214 = Methodref          #103.#213     // kotlin/text/StringsKt.takeLast:(Ljava/lang/String;I)Ljava/lang/String;
  #215 = Utf8               ffmpeg failed: \u0001
  #216 = String             #215          // ffmpeg failed: \u0001
  #217 = InvokeDynamic      #5:#180       // #5:makeConcatWithConstants:(Ljava/lang/String;)Ljava/lang/String;
  #218 = Methodref          #210.#39      // java/lang/IllegalStateException."<init>":(Ljava/lang/String;)V
  #219 = Utf8               delete
  #220 = NameAndType        #219:#55      // delete:()Z
  #221 = Methodref          #42.#220      // java/io/File.delete:()Z
  #222 = Utf8               $i$a$-require-AudioSegmentDownloader$cutSegmentFromLocal$1
  #223 = Utf8               I
  #224 = Utf8               $i$a$-apply-AudioSegmentDownloader$cutSegmentFromLocal$outputDir$1
  #225 = Utf8               $this$cutSegmentFromLocal_u24lambda_u241
  #226 = Utf8               Ljava/io/File;
  #227 = Utf8               $i$a$-ifBlank-AudioSegmentDownloader$cutSegmentFromLocal$sourceExt$1
  #228 = Utf8               $i$a$-buildString-AudioSegmentDownloader$cutSegmentFromLocal$copyCmd$1
  #229 = Utf8               $this$cutSegmentFromLocal_u24lambda_u243
  #230 = Utf8               Ljava/lang/StringBuilder;
  #231 = Utf8               $i$a$-buildString-AudioSegmentDownloader$cutSegmentFromLocal$transcodeCmd$1
  #232 = Utf8               $this$cutSegmentFromLocal_u24lambda_u244
  #233 = Utf8               $i$a$-runCatching-AudioSegmentDownloader$cutSegmentFromLocal$logs$1
  #234 = Utf8               $this$cutSegmentFromLocal_u24lambda_u245
  #235 = Utf8               logs
  #236 = Utf8               Ljava/lang/String;
  #237 = Utf8               outputDir
  #238 = Utf8               baseName
  #239 = Utf8               sourceExt
  #240 = Utf8               preferredCopyExt
  #241 = Utf8               copyOut
  #242 = Utf8               localIn
  #243 = Utf8               copyCmd
  #244 = Utf8               copySession
  #245 = Utf8               Lcom/arthenica/ffmpegkit/FFmpegSession;
  #246 = Utf8               transOut
  #247 = Utf8               transcodeCmd
  #248 = Utf8               transSession
  #249 = Utf8               startSec
  #250 = Utf8               endSec
  #251 = Utf8               \"
  #252 = String             #251          // \"
  #253 = Utf8               \\\"
  #254 = String             #253          // \\\"
  #255 = Utf8               replace$default
  #256 = Utf8               (Ljava/lang/String;Ljava/lang/String;Ljava/lang/String;ZILjava/lang/Object;)Ljava/lang/String;
  #257 = NameAndType        #255:#256     // replace$default:(Ljava/lang/String;Ljava/lang/String;Ljava/lang/String;ZILjava/lang/Object;)Ljava/lang/String;
  #258 = Methodref          #103.#257     // kotlin/text/StringsKt.replace$default:(Ljava/lang/String;Ljava/lang/String;Ljava/lang/String;ZILjava/lang/Object;)Ljava/lang/String;
  #259 = Utf8               value
  #260 = Utf8               Lkotlin/Metadata;
  #261 = Utf8               mv
  #262 = Integer            2
  #263 = Integer            0
  #264 = Utf8               k
  #265 = Integer            1
  #266 = Utf8               xi
  #267 = Integer            48
  #268 = Utf8               d1
  #269 = Utf8               \u0000&\n\u0002\u0018\u0002\n\u0002\u0010\u0000\n\u0000\n\u0002\u0018\u0002\n\u0002\b\u0003\n\u0002\u0018\u0002\n\u0000\n\u0002\u0010\u000e\n\u0000\n\u0002\u0010\b\n\u0002\b\u0004\u0018\u00002\u00020\u0001B\u000f\u0012\u0006\u0010\u0002\u001a\u00020\u0003?\u0006\u0004\b\u0004\u0010\u0005J\u001e\u0010\u0006\u001a\u00020\u00072\u0006\u0010\b\u001a\u00020\t2\u0006\u0010\n\u001a\u00020\u000b2\u0006\u0010\f\u001a\u00020\u000bJ\u0010\u0010\r\u001a\u00020\t2\u0006\u0010\u000e\u001a\u00020\tH\u0002R\u000e\u0010\u0002\u001a\u00020\u0003X\u0082\u0004?\u0006\u0002\n\u0000��\u0006\u000f
  #270 = Utf8               d2
  #271 = Utf8               app_debug
  #272 = Utf8               AudioSegmentDownloader.kt
  #273 = Utf8               Lkotlin/jvm/internal/SourceDebugExtension;
  #274 = Utf8               SMAP\nAudioSegmentDownloader.kt\nKotlin\n*S Kotlin\n*F\n+ 1 AudioSegmentDownloader.kt\ncom/example/project3/AudioSegmentDownloader\n+ 2 fake.kt\nkotlin/jvm/internal/FakeKt\n*L\n1#1,46:1\n1#2:47\n*E\n
  #275 = Utf8               RuntimeInvisibleAnnotations
  #276 = Utf8               Code
  #277 = Utf8               LineNumberTable
  #278 = Utf8               LocalVariableTable
  #279 = Utf8               RuntimeInvisibleParameterAnnotations
  #280 = Utf8               StackMapTable
  #281 = Utf8               SourceFile
  #282 = Utf8               SourceDebugExtension
  #283 = Utf8               RuntimeVisibleAnnotations
  #284 = Utf8               BootstrapMethods
{
  private final android.content.Context context;
    descriptor: Landroid/content/Context;
    flags: (0x0012) ACC_PRIVATE, ACC_FINAL
    RuntimeInvisibleAnnotations:
      0: #7()
        org.jetbrains.annotations.NotNull

  public com.example.project3.AudioSegmentDownloader(android.content.Context);
    descriptor: (Landroid/content/Context;)V
    flags: (0x0001) ACC_PUBLIC
    Code:
      stack=2, locals=2, args_size=2
         0: aload_1
         1: ldc           #9                  // String context
         3: invokestatic  #15                 // Method kotlin/jvm/internal/Intrinsics.checkNotNullParameter:(Ljava/lang/Object;Ljava/lang/String;)V
         6: aload_0
         7: invokespecial #18                 // Method java/lang/Object."<init>":()V
        10: aload_0
        11: aload_1
        12: putfield      #21                 // Field context:Landroid/content/Context;
        15: return
      LineNumberTable:
        line 7: 6
      LocalVariableTable:
        Start  Length  Slot  Name   Signature
            0      16     0  this   Lcom/example/project3/AudioSegmentDownloader;
            0      16     1 context   Landroid/content/Context;
    RuntimeInvisibleParameterAnnotations:
      parameter 0:
        0: #7()
          org.jetbrains.annotations.NotNull

  public final java.io.File cutSegmentFromLocal(java.lang.String, int, int);
    descriptor: (Ljava/lang/String;II)Ljava/io/File;
    flags: (0x0011) ACC_PUBLIC, ACC_FINAL
    Code:
      stack=5, locals=19, args_size=4
         0: aload_1
         1: ldc           #29                 // String localSourcePath
         3: invokestatic  #15                 // Method kotlin/jvm/internal/Intrinsics.checkNotNullParameter:(Ljava/lang/Object;Ljava/lang/String;)V
         6: iload_3
         7: iload_2
         8: if_icmple     15
        11: iconst_1
        12: goto          16
        15: iconst_0
        16: ifne          39
        19: iconst_0
        20: istore        5
        22: ldc           #31                 // String endSec must be greater than startSec
        24: astore        5
        26: new           #33                 // class java/lang/IllegalArgumentException
        29: dup
        30: aload         5
        32: invokevirtual #37                 // Method java/lang/Object.toString:()Ljava/lang/String;
        35: invokespecial #40                 // Method java/lang/IllegalArgumentException."<init>":(Ljava/lang/String;)V
        38: athrow
        39: new           #42                 // class java/io/File
        42: dup
        43: aload_0
        44: getfield      #21                 // Field context:Landroid/content/Context;
        47: aconst_null
        48: invokevirtual #48                 // Method android/content/Context.getExternalFilesDir:(Ljava/lang/String;)Ljava/io/File;
        51: ldc           #50                 // String segments
        53: invokespecial #53                 // Method java/io/File."<init>":(Ljava/io/File;Ljava/lang/String;)V
        56: astore        5
        58: aload         5
        60: astore        6
        62: iconst_0
        63: istore        7
        65: aload         6
        67: invokevirtual #57                 // Method java/io/File.mkdirs:()Z
        70: pop
        71: aload         5
        73: astore        4
        75: invokestatic  #63                 // Method java/lang/System.currentTimeMillis:()J
        78: iload_2
        79: iload_3
        80: invokedynamic #75,  0             // InvokeDynamic #0:makeConcatWithConstants:(JII)Ljava/lang/String;
        85: astore        5
        87: new           #42                 // class java/io/File
        90: dup
        91: aload_1
        92: invokespecial #76                 // Method java/io/File."<init>":(Ljava/lang/String;)V
        95: invokestatic  #82                 // Method kotlin/io/FilesKt.getExtension:(Ljava/io/File;)Ljava/lang/String;
        98: getstatic     #88                 // Field java/util/Locale.ROOT:Ljava/util/Locale;
       101: invokevirtual #94                 // Method java/lang/String.toLowerCase:(Ljava/util/Locale;)Ljava/lang/String;
       104: dup
       105: ldc           #96                 // String toLowerCase(...)
       107: invokestatic  #99                 // Method kotlin/jvm/internal/Intrinsics.checkNotNullExpressionValue:(Ljava/lang/Object;Ljava/lang/String;)V
       110: checkcast     #101                // class java/lang/CharSequence
       113: astore        7
       115: aload         7
       117: invokestatic  #107                // Method kotlin/text/StringsKt.isBlank:(Ljava/lang/CharSequence;)Z
       120: ifeq          131
       123: iconst_0
       124: istore        8
       126: ldc           #109                // String webm
       128: goto          133
       131: aload         7
       133: checkcast     #90                 // class java/lang/String
       136: astore        6
       138: aload         6
       140: invokevirtual #113                // Method java/lang/String.hashCode:()I
       143: lookupswitch  { // 3

                   96323: 189

                  106458: 202

                  108273: 176
                 default: 217
            }
       176: aload         6
       178: ldc           #115                // String mp4
       180: invokevirtual #119                // Method java/lang/String.equals:(Ljava/lang/Object;)Z
       183: ifne          212
       186: goto          217
       189: aload         6
       191: ldc           #121                // String aac
       193: invokevirtual #119                // Method java/lang/String.equals:(Ljava/lang/Object;)Z
       196: ifne          212
       199: goto          217
       202: aload         6
       204: ldc           #123                // String m4a
       206: invokevirtual #119                // Method java/lang/String.equals:(Ljava/lang/Object;)Z
       209: ifeq          217
       212: ldc           #123                // String m4a
       214: goto          219
       217: ldc           #109                // String webm
       219: astore        7
       221: new           #42                 // class java/io/File
       224: dup
       225: aload         4
       227: aload         5
       229: aload         7
       231: invokedynamic #128,  0            // InvokeDynamic #1:makeConcatWithConstants:(Ljava/lang/String;Ljava/lang/String;)Ljava/lang/String;
       236: invokespecial #53                 // Method java/io/File."<init>":(Ljava/io/File;Ljava/lang/String;)V
       239: astore        8
       241: aload_0
       242: aload_1
       243: invokespecial #132                // Method escapeForCli:(Ljava/lang/String;)Ljava/lang/String;
       246: astore        9
       248: new           #134                // class java/lang/StringBuilder
       251: dup
       252: invokespecial #135                // Method java/lang/StringBuilder."<init>":()V
       255: astore        11
       257: aload         11
       259: astore        12
       261: iconst_0
       262: istore        13
       264: aload         12
       266: ldc           #137                // String -y -hide_banner -loglevel error -nostdin
       268: invokevirtual #141                // Method java/lang/StringBuilder.append:(Ljava/lang/String;)Ljava/lang/StringBuilder;
       271: pop
       272: aload         12
       274: iload_2
       275: iload_3
       276: aload         9
       278: aload         8
       280: invokevirtual #144                // Method java/io/File.getAbsolutePath:()Ljava/lang/String;
       283: invokedynamic #149,  0            // InvokeDynamic #2:makeConcatWithConstants:(IILjava/lang/String;Ljava/lang/String;)Ljava/lang/String;
       288: invokevirtual #141                // Method java/lang/StringBuilder.append:(Ljava/lang/String;)Ljava/lang/StringBuilder;
       291: pop
       292: nop
       293: aload         11
       295: invokevirtual #150                // Method java/lang/StringBuilder.toString:()Ljava/lang/String;
       298: dup
       299: ldc           #152                // String toString(...)
       301: invokestatic  #99                 // Method kotlin/jvm/internal/Intrinsics.checkNotNullExpressionValue:(Ljava/lang/Object;Ljava/lang/String;)V
       304: astore        10
       306: aload         10
       308: invokestatic  #158                // Method com/arthenica/ffmpegkit/FFmpegKit.execute:(Ljava/lang/String;)Lcom/arthenica/ffmpegkit/FFmpegSession;
       311: astore        11
       313: aload         11
       315: invokevirtual #164                // Method com/arthenica/ffmpegkit/FFmpegSession.getReturnCode:()Lcom/arthenica/ffmpegkit/ReturnCode;
       318: invokevirtual #169                // Method com/arthenica/ffmpegkit/ReturnCode.isValueSuccess:()Z
       321: ifeq          347
       324: aload         8
       326: invokevirtual #172                // Method java/io/File.exists:()Z
       329: ifeq          347
       332: aload         8
       334: invokevirtual #175                // Method java/io/File.length:()J
       337: ldc2_w        #176                // long 1024l
       340: lcmp
       341: ifle          347
       344: aload         8
       346: areturn
       347: new           #42                 // class java/io/File
       350: dup
       351: aload         4
       353: aload         5
       355: invokedynamic #181,  0            // InvokeDynamic #3:makeConcatWithConstants:(Ljava/lang/String;)Ljava/lang/String;
       360: invokespecial #53                 // Method java/io/File."<init>":(Ljava/io/File;Ljava/lang/String;)V
       363: astore        12
       365: new           #134                // class java/lang/StringBuilder
       368: dup
       369: invokespecial #135                // Method java/lang/StringBuilder."<init>":()V
       372: astore        14
       374: aload         14
       376: astore        15
       378: iconst_0
       379: istore        16
       381: aload         15
       383: ldc           #137                // String -y -hide_banner -loglevel error -nostdin
       385: invokevirtual #141                // Method java/lang/StringBuilder.append:(Ljava/lang/String;)Ljava/lang/StringBuilder;
       388: pop
       389: aload         15
       391: iload_2
       392: iload_3
       393: aload         9
       395: aload         12
       397: invokevirtual #144                // Method java/io/File.getAbsolutePath:()Ljava/lang/String;
       400: invokedynamic #184,  0            // InvokeDynamic #4:makeConcatWithConstants:(IILjava/lang/String;Ljava/lang/String;)Ljava/lang/String;
       405: invokevirtual #141                // Method java/lang/StringBuilder.append:(Ljava/lang/String;)Ljava/lang/StringBuilder;
       408: pop
       409: nop
       410: aload         14
       412: invokevirtual #150                // Method java/lang/StringBuilder.toString:()Ljava/lang/String;
       415: dup
       416: ldc           #152                // String toString(...)
       418: invokestatic  #99                 // Method kotlin/jvm/internal/Intrinsics.checkNotNullExpressionValue:(Ljava/lang/Object;Ljava/lang/String;)V
       421: astore        13
       423: aload         13
       425: invokestatic  #158                // Method com/arthenica/ffmpegkit/FFmpegKit.execute:(Ljava/lang/String;)Lcom/arthenica/ffmpegkit/FFmpegSession;
       428: astore        14
       430: aload         14
       432: invokevirtual #164                // Method com/arthenica/ffmpegkit/FFmpegSession.getReturnCode:()Lcom/arthenica/ffmpegkit/ReturnCode;
       435: invokevirtual #169                // Method com/arthenica/ffmpegkit/ReturnCode.isValueSuccess:()Z
       438: ifeq          461
       441: aload         12
       443: invokevirtual #172                // Method java/io/File.exists:()Z
       446: ifeq          461
       449: aload         12
       451: invokevirtual #175                // Method java/io/File.length:()J
       454: ldc2_w        #176                // long 1024l
       457: lcmp
       458: ifgt          559
       461: aload_0
       462: astore        16
       464: nop
       465: getstatic     #190                // Field kotlin/Result.Companion:Lkotlin/Result$Companion;
       468: pop
       469: aload         16
       471: checkcast     #2                  // class com/example/project3/AudioSegmentDownloader
       474: astore        17
       476: iconst_0
       477: istore        18
       479: aload         14
       481: invokevirtual #193                // Method com/arthenica/ffmpegkit/FFmpegSession.getAllLogsAsString:()Ljava/lang/String;
       484: invokestatic  #197                // Method kotlin/Result."constructor-impl":(Ljava/lang/Object;)Ljava/lang/Object;
       487: astore        17
       489: goto          508
       492: astore        18
       494: getstatic     #190                // Field kotlin/Result.Companion:Lkotlin/Result$Companion;
       497: pop
       498: aload         18
       500: invokestatic  #203                // Method kotlin/ResultKt.createFailure:(Ljava/lang/Throwable;)Ljava/lang/Object;
       503: invokestatic  #197                // Method kotlin/Result."constructor-impl":(Ljava/lang/Object;)Ljava/lang/Object;
       506: astore        17
       508: aload         17
       510: astore        16
       512: aload         16
       514: invokestatic  #206                // Method kotlin/Result."isFailure-impl":(Ljava/lang/Object;)Z
       517: ifeq          524
       520: aconst_null
       521: goto          526
       524: aload         16
       526: checkcast     #90                 // class java/lang/String
       529: dup
       530: ifnonnull     536
       533: pop
       534: ldc           #208                // String
       536: astore        15
       538: new           #210                // class java/lang/IllegalStateException
       541: dup
       542: aload         15
       544: sipush        600
       547: invokestatic  #214                // Method kotlin/text/StringsKt.takeLast:(Ljava/lang/String;I)Ljava/lang/String;
       550: invokedynamic #217,  0            // InvokeDynamic #5:makeConcatWithConstants:(Ljava/lang/String;)Ljava/lang/String;
       555: invokespecial #218                // Method java/lang/IllegalStateException."<init>":(Ljava/lang/String;)V
       558: athrow
       559: aload         8
       561: invokevirtual #221                // Method java/io/File.delete:()Z
       564: pop
       565: aload         12
       567: areturn
      Exception table:
         from    to  target type
           464   489   492   Class java/lang/Throwable
      StackMapTable: number_of_entries = 19
        frame_type = 15 /* same */
        frame_type = 64 /* same_locals_1_stack_item */
          stack = [ int ]
        frame_type = 22 /* same */
        frame_type = 255 /* full_frame */
          offset_delta = 91
          locals = [ class com/example/project3/AudioSegmentDownloader, class java/lang/String, int, int, class java/io/File, class java/lang/String, class java/io/File, class java/lang/CharSequence ]
          stack = []
        frame_type = 65 /* same_locals_1_stack_item */
          stack = [ class java/lang/Object ]
        frame_type = 255 /* full_frame */
          offset_delta = 42
          locals = [ class com/example/project3/AudioSegmentDownloader, class java/lang/String, int, int, class java/io/File, class java/lang/String, class java/lang/String, class java/lang/CharSequence ]
          stack = []
        frame_type = 12 /* same */
        frame_type = 12 /* same */
        frame_type = 9 /* same */
        frame_type = 4 /* same */
        frame_type = 65 /* same_locals_1_stack_item */
          stack = [ class java/lang/String ]
        frame_type = 255 /* full_frame */
          offset_delta = 127
          locals = [ class com/example/project3/AudioSegmentDownloader, class java/lang/String, int, int, class java/io/File, class java/lang/String, class java/lang/String, class java/lang/String, class java/io/File, class java/lang/String, class java/lang/String, class com/arthenica/ffmpegkit/FFmpegSession, class java/lang/StringBuilder, int ]
          stack = []
        frame_type = 255 /* full_frame */
          offset_delta = 113
          locals = [ class com/example/project3/AudioSegmentDownloader, class java/lang/String, int, int, class java/io/File, class java/lang/String, class java/lang/String, class java/lang/String, class java/io/File, class java/lang/String, class java/lang/String, class com/arthenica/ffmpegkit/FFmpegSession, class java/io/File, class java/lang/String, class com/arthenica/ffmpegkit/FFmpegSession, class java/lang/StringBuilder, int ]
          stack = []
        frame_type = 255 /* full_frame */
          offset_delta = 30
          locals = [ class com/example/project3/AudioSegmentDownloader, class java/lang/String, int, int, class java/io/File, class java/lang/String, class java/lang/String, class java/lang/String, class java/io/File, class java/lang/String, class java/lang/String, class com/arthenica/ffmpegkit/FFmpegSession, class java/io/File, class java/lang/String, class com/arthenica/ffmpegkit/FFmpegSession, class java/lang/StringBuilder, class com/example/project3/AudioSegmentDownloader ]
          stack = [ class java/lang/Throwable ]
        frame_type = 252 /* append */
          offset_delta = 15
          locals = [ class java/lang/Object ]
        frame_type = 255 /* full_frame */
          offset_delta = 15
          locals = [ class com/example/project3/AudioSegmentDownloader, class java/lang/String, int, int, class java/io/File, class java/lang/String, class java/lang/String, class java/lang/String, class java/io/File, class java/lang/String, class java/lang/String, class com/arthenica/ffmpegkit/FFmpegSession, class java/io/File, class java/lang/String, class com/arthenica/ffmpegkit/FFmpegSession, class java/lang/StringBuilder, class java/lang/Object, class java/lang/Object ]
          stack = []
        frame_type = 65 /* same_locals_1_stack_item */
          stack = [ class java/lang/Object ]
        frame_type = 73 /* same_locals_1_stack_item */
          stack = [ class java/lang/String ]
        frame_type = 255 /* full_frame */
          offset_delta = 22
          locals = [ class com/example/project3/AudioSegmentDownloader, class java/lang/String, int, int, class java/io/File, class java/lang/String, class java/lang/String, class java/lang/String, class java/io/File, class java/lang/String, class java/lang/String, class com/arthenica/ffmpegkit/FFmpegSession, class java/io/File, class java/lang/String, class com/arthenica/ffmpegkit/FFmpegSession, class java/lang/StringBuilder, int ]
          stack = []
      LineNumberTable:
        line 13: 6
        line 47: 19
        line 13: 22
        line 13: 24
        line 14: 39
        line 47: 62
        line 14: 65
        line 14: 71
        line 14: 73
        line 15: 75
        line 16: 87
        line 16: 115
        line 47: 123
        line 16: 126
        line 16: 128
        line 16: 133
        line 17: 138
        line 18: 221
        line 19: 241
        line 21: 248
        line 22: 264
        line 23: 272
        line 24: 292
        line 21: 293
        line 21: 304
        line 25: 306
        line 26: 313
        line 27: 344
        line 30: 347
        line 31: 365
        line 32: 381
        line 33: 389
        line 34: 409
        line 31: 410
        line 31: 421
        line 35: 423
        line 36: 430
        line 37: 461
        line 47: 476
        line 37: 479
        line 37: 484
        line 37: 512
        line 37: 529
        line 37: 536
        line 38: 538
        line 40: 559
        line 41: 565
      LocalVariableTable:
        Start  Length  Slot  Name   Signature
           22       2     5 $i$a$-require-AudioSegmentDownloader$cutSegmentFromLocal$1   I
           65       6     7 $i$a$-apply-AudioSegmentDownloader$cutSegmentFromLocal$outputDir$1   I
           62       9     6 $this$cutSegmentFromLocal_u24lambda_u241   Ljava/io/File;
          126       2     8 $i$a$-ifBlank-AudioSegmentDownloader$cutSegmentFromLocal$sourceExt$1   I
          264      29    13 $i$a$-buildString-AudioSegmentDownloader$cutSegmentFromLocal$copyCmd$1   I
          261      32    12 $this$cutSegmentFromLocal_u24lambda_u243   Ljava/lang/StringBuilder;
          381      29    16 $i$a$-buildString-AudioSegmentDownloader$cutSegmentFromLocal$transcodeCmd$1   I
          378      32    15 $this$cutSegmentFromLocal_u24lambda_u244   Ljava/lang/StringBuilder;
          479       5    18 $i$a$-runCatching-AudioSegmentDownloader$cutSegmentFromLocal$logs$1   I
          476       8    17 $this$cutSegmentFromLocal_u24lambda_u245   Lcom/example/project3/AudioSegmentDownloader;
          538      21    15  logs   Ljava/lang/String;
           75     493     4 outputDir   Ljava/io/File;
           87     481     5 baseName   Ljava/lang/String;
          138     430     6 sourceExt   Ljava/lang/String;
          221     347     7 preferredCopyExt   Ljava/lang/String;
          241     327     8 copyOut   Ljava/io/File;
          248     320     9 localIn   Ljava/lang/String;
          306     262    10 copyCmd   Ljava/lang/String;
          313     255    11 copySession   Lcom/arthenica/ffmpegkit/FFmpegSession;
          365     203    12 transOut   Ljava/io/File;
          423     145    13 transcodeCmd   Ljava/lang/String;
          430     138    14 transSession   Lcom/arthenica/ffmpegkit/FFmpegSession;
            0     568     0  this   Lcom/example/project3/AudioSegmentDownloader;
            0     568     1 localSourcePath   Ljava/lang/String;
            0     568     2 startSec   I
            0     568     3 endSec   I
    RuntimeInvisibleAnnotations:
      0: #7()
        org.jetbrains.annotations.NotNull
    RuntimeInvisibleParameterAnnotations:
      parameter 0:
        0: #7()
          org.jetbrains.annotations.NotNull
      parameter 1:
      parameter 2:

  private final java.lang.String escapeForCli(java.lang.String);
    descriptor: (Ljava/lang/String;)Ljava/lang/String;
    flags: (0x0012) ACC_PRIVATE, ACC_FINAL
    Code:
      stack=6, locals=2, args_size=2
         0: aload_1
         1: ldc           #252                // String \"
         3: ldc           #254                // String \\\"
         5: iconst_0
         6: iconst_4
         7: aconst_null
         8: invokestatic  #258                // Method kotlin/text/StringsKt.replace$default:(Ljava/lang/String;Ljava/lang/String;Ljava/lang/String;ZILjava/lang/Object;)Ljava/lang/String;
        11: areturn
      LineNumberTable:
        line 44: 0
      LocalVariableTable:
        Start  Length  Slot  Name   Signature
            0      12     0  this   Lcom/example/project3/AudioSegmentDownloader;
            0      12     1 value   Ljava/lang/String;
}
SourceFile: "AudioSegmentDownloader.kt"
SourceDebugExtension:
  SMAP
  AudioSegmentDownloader.kt
  Kotlin
  *S Kotlin
  *F
  + 1 AudioSegmentDownloader.kt
  com/example/project3/AudioSegmentDownloader
  + 2 fake.kt
  kotlin/jvm/internal/FakeKt
  *L
  1#1,46:1
  1#2:47
  *E
RuntimeVisibleAnnotations:
  0: #260(#261=[I#262,I#263,I#263],#264=I#265,#266=I#267,#268=[s#269],#270=[s#23,s#207,s#8,s#19,s#5,s#6,s#24,s#226,s#28,s#207,s#249,s#207,s#250,s#129,s#259,s#271])
    kotlin.Metadata(
      mv=[2,0,0]
      k=1
      xi=48
      d1=["\u0000&\n\u0002\u0018\u0002\n\u0002\u0010\u0000\n\u0000\n\u0002\u0018\u0002\n\u0002\b\u0003\n\u0002\u0018\u0002\n\u0000\n\u0002\u0010\u000e\n\u0000\n\u0002\u0010\b\n\u0002\b\u0004\u0018\u00002\u00020\u0001B\u000f\u0012\u0006\u0010\u0002\u001a\u00020\u0003?\u0006\u0004\b\u0004\u0010\u0005J\u001e\u0010\u0006\u001a\u00020\u00072\u0006\u0010\b\u001a\u00020\t2\u0006\u0010\n\u001a\u00020\u000b2\u0006\u0010\f\u001a\u00020\u000bJ\u0010\u0010\r\u001a\u00020\t2\u0006\u0010\u000e\u001a\u00020\tH\u0002R\u000e\u0010\u0002\u001a\u00020\u0003X\u0082\u0004?\u0006\u0002\n\u0000��\u0006\u000f"]
      d2=["Lcom/example/project3/AudioSegmentDownloader;","","context","Landroid/content/Context;","<init>","(Landroid/content/Context;)V","cutSegmentFromLocal","Ljava/io/File;","localSourcePath","","startSec","","endSec","escapeForCli","value","app_debug"]
    )
RuntimeInvisibleAnnotations:
  0: #273(#259=[s#274])
    kotlin.jvm.internal.SourceDebugExtension(
      value=["SMAP\nAudioSegmentDownloader.kt\nKotlin\n*S Kotlin\n*F\n+ 1 AudioSegmentDownloader.kt\ncom/example/project3/AudioSegmentDownloader\n+ 2 fake.kt\nkotlin/jvm/internal/FakeKt\n*L\n1#1,46:1\n1#2:47\n*E\n"]
    )
BootstrapMethods:
  0: #72 REF_invokeStatic java/lang/invoke/StringConcatFactory.makeConcatWithConstants:(Ljava/lang/invoke/MethodHandles$Lookup;Ljava/lang/String;Ljava/lang/invoke/MethodType;Ljava/lang/String;[Ljava/lang/Object;)Ljava/lang/invoke/CallSite;
    Method arguments:
      #65 seg-\u0001-\u0001s-\u0001s
  1: #72 REF_invokeStatic java/lang/invoke/StringConcatFactory.makeConcatWithConstants:(Ljava/lang/invoke/MethodHandles$Lookup;Ljava/lang/String;Ljava/lang/invoke/MethodType;Ljava/lang/String;[Ljava/lang/Object;)Ljava/lang/invoke/CallSite;
    Method arguments:
      #125 \u0001.\u0001
  2: #72 REF_invokeStatic java/lang/invoke/StringConcatFactory.makeConcatWithConstants:(Ljava/lang/invoke/MethodHandles$Lookup;Ljava/lang/String;Ljava/lang/invoke/MethodType;Ljava/lang/String;[Ljava/lang/Object;)Ljava/lang/invoke/CallSite;
    Method arguments:
      #146 -ss \u0001 -to \u0001 -i \"\u0001\" -vn -c:a copy \"\u0001\"
  3: #72 REF_invokeStatic java/lang/invoke/StringConcatFactory.makeConcatWithConstants:(Ljava/lang/invoke/MethodHandles$Lookup;Ljava/lang/String;Ljava/lang/invoke/MethodType;Ljava/lang/String;[Ljava/lang/Object;)Ljava/lang/invoke/CallSite;
    Method arguments:
      #179 \u0001.opus
  4: #72 REF_invokeStatic java/lang/invoke/StringConcatFactory.makeConcatWithConstants:(Ljava/lang/invoke/MethodHandles$Lookup;Ljava/lang/String;Ljava/lang/invoke/MethodType;Ljava/lang/String;[Ljava/lang/Object;)Ljava/lang/invoke/CallSite;
    Method arguments:
      #183 -ss \u0001 -to \u0001 -i \"\u0001\" -vn -c:a libopus -b:a 64k \"\u0001\"
  5: #72 REF_invokeStatic java/lang/invoke/StringConcatFactory.makeConcatWithConstants:(Ljava/lang/invoke/MethodHandles$Lookup;Ljava/lang/String;Ljava/lang/invoke/MethodType;Ljava/lang/String;[Ljava/lang/Object;)Ljava/lang/invoke/CallSite;
    Method arguments:
      #216 ffmpeg failed: \u0001
